liquid_crystals/__init__.py
liquid_crystals/cli.py
liquid_crystals/display.py
liquid_crystals/fields.py
liquid_crystals/lc.py
liquid_crystals-0.2.1.dist-info/LICENSE
liquid_crystals-0.2.1.dist-info/METADATA
liquid_crystals-0.2.1.dist-info/WHEEL
liquid_crystals-0.2.1.dist-info/entry_points.txt
liquid_crystals-0.2.1.dist-info/top_level.txt
liquid_crystals-0.2.1.dist-info/RECORD
