Metadata-Version: 2.1
Name: liquid-crystals
Version: 0.2.1
Summary: A liquid crystal simulation and visualization package
Home-page: https://github.com/yourusername/liquid-crystals
Author: [Your Name]
Author-email: [your.email@example.com]
Project-URL: Bug Tracker, https://github.com/yourusername/liquid-crystals/issues
Classifier: Programming Language :: Python :: 3
Classifier: License :: OSI Approved :: MIT License
Classifier: Operating System :: OS Independent
Classifier: Topic :: Scientific/Engineering :: Physics
Classifier: Topic :: Scientific/Engineering :: Visualization
Requires-Python: >=3.7
License-File: LICENSE
Requires-Dist: numpy
Requires-Dist: scipy
Requires-Dist: matplotlib
Requires-Dist: click
